{
  "1.0.1": "отдел программы, руководитель",
  "1.0.2": "отедл программы, event-менеджер",
  "1.0.3": "отдел программы, менеджер по работе с партнёрами",
  "2.1.4": "творческий отдел, заместитель руководителя по сценическому направлению",
  "2.1.5": "творческий отдел, сценарист",
  "2.1.6": "творческий отдел, композитор",
  "2.1.7": "творческий отдел, хореограф",
  "2.1.8": "творческий отдел, художник по свету",
  "2.1.9": "творческий отдел, звукорежиссер",
  "2.1.10": "творческий отдел, видеограф",
  "2.1.3": "творческий отдел, менеджер по работе спартнерами по сценическому направлению",
  "2.1.11": "творческий отдел, технический специалист",
  "2.2.4": "творческий отдел, заместитель руководителя по направлению стендовой сессии",
  "2.2.2": "творческий отдел, event менеджер",
  "2.2.3": "творческий отдел, менеджер по работе с партнерами по направлению стендовой сессии",
  "3.0.2": "отдел партнёров, менеджер по работе с партнёрами",
  "3.0.3": "отдел партнёров, менеджер по работе с партнёрами",
  "4.3.4": "отдел смм, заместитель руководителя по направлению социальные сети",
  "4.3.12": "отдел смм, контент менеджер",
  "4.3.13": "отдел смм, контент менеджер со знанием китайского",
  "4.3.14": "отдел смм, рилсмейкер",
  "4.3.15": "отдел смм, аналитик",
  "4.3.16": "отдел смм, комьюнити менеджер",
  "4.3.3": "менеджер по работе с партнерами по направлению социальные сети",
  "4.4.4": "отдел смм, заместитель руководителя по направлению медиа шоу",
  "4.4.17": "отдел смм, продюссер медиа шоу",
  "4.4.5": "отдел смм, сценарист",
  "4.4.18": "отдел смм, режиссер медиао шоу",
  "4.4.9": "отдел смм, звукорежиссер",
  "4.4.19": "отдел смм, моушен дизайнер",
  "4.4.10": "отдел смм, видеограф",
  "4.4.3": "отдел смм, менеджер по работе с партнерами по направлению медиао шоу",
  "5.0.20": "отдел дизайна, дизайнер мерча",
  "5.0.21": "отдел дизайна, диджитал дизайнер",
  "5.0.22": "отдел дизайна, 3д моделлер",
  "5.0.23": "отдел дизайна, иллюстратор",
  "5.0.19": "отдел дизайна, моушен дизайнер",
  "6.0.24": "отдел логистики, логист",
  "6.0.25": "отдел логистики, it-специалист",
  "7.0.1": "выставочный отдел, руководитель",
  "7.0.2": "выставочный отдел, event-менеджер",
  "7.0.3": "выставочный отдел, менеджер по работе с партнёрами"
}